[
    {
        "input": [
            300.5,
            297.5,
            0.5,
            -143.5,
            143.50087107749556
        ],
        "output": [
            0,
            0,
            1,
            0
        ]
    },
    {
        "input": [
            337.5,
            230.5,
            37.5,
            180.5,
            184.3542784965947
        ],
        "output": [
            1,
            0,
            0,
            0
        ]
    },
    {
        "input": [
            275,
            293,
            -25,
            243,
            244.28262320517192
        ],
        "output": [
            1,
            0,
            0,
            0
        ]
    },
    {
        "input": [
            370.5,
            170.5,
            270.5,
            -79.5,
            281.9405965802016
        ],
        "output": [
            0,
            0,
            0,
            1
        ]
    },
    {
        "input": [
            265.5,
            332.5,
            -34.5,
            -108.5,
            113.852975367357
        ],
        "output": [
            0,
            0,
            1,
            0
        ]
    },
    {
        "input": [
            328,
            270,
            28,
            -171,
            173.27723451163456
        ],
        "output": [
            0,
            0,
            1,
            0
        ]
    },
    {
        "input": [
            285.5,
            312.5,
            -14.5,
            -128.5,
            129.31550564414152
        ],
        "output": [
            0,
            0,
            1,
            0
        ]
    },
    {
        "input": [
            222.5,
            222.5,
            -277.5,
            -27.5,
            278.859283510519
        ],
        "output": [
            0,
            1,
            0,
            0
        ]
    },
    {
        "input": [
            410.5,
            210.5,
            310.5,
            -39.5,
            313.00239615696233
        ],
        "output": [
            0,
            0,
            0,
            1
        ]
    },
    {
        "input": [
            325.5,
            272.5,
            25.5,
            -168.5,
            170.41860227099622
        ],
        "output": [
            0,
            0,
            1,
            0
        ]
    },
    {
        "input": [
            273,
            325,
            -27,
            -116,
            119.10079764636339
        ],
        "output": [
            0,
            0,
            1,
            0
        ]
    },
    {
        "input": [
            375,
            193,
            75,
            143,
            161.47445618425226
        ],
        "output": [
            1,
            0,
            0,
            0
        ]
    },
    {
        "input": [
            418,
            218,
            318,
            -32,
            319.60600745292635
        ],
        "output": [
            0,
            0,
            0,
            1
        ]
    },
    {
        "input": [
            355.5,
            242.5,
            55.5,
            -198.5,
            206.11283317639393
        ],
        "output": [
            0,
            0,
            1,
            0
        ]
    },
    {
        "input": [
            348,
            148,
            248,
            -102,
            268.15667062372324
        ],
        "output": [
            0,
            0,
            0,
            1
        ]
    },
    {
        "input": [
            220,
            220,
            -280,
            -30,
            281.60255680657446
        ],
        "output": [
            0,
            1,
            0,
            0
        ]
    },
    {
        "input": [
            405.5,
            205.5,
            305.5,
            -44.5,
            308.7239867583988
        ],
        "output": [
            0,
            0,
            0,
            1
        ]
    },
    {
        "input": [
            355.5,
            155.5,
            255.5,
            -94.5,
            272.41604211206067
        ],
        "output": [
            0,
            0,
            0,
            1
        ]
    },
    {
        "input": [
            298,
            98,
            198,
            -152,
            249.61570463414355
        ],
        "output": [
            0,
            0,
            0,
            1
        ]
    },
    {
        "input": [
            265,
            265,
            -235,
            15,
            235.47823678633233
        ],
        "output": [
            0,
            1,
            0,
            0
        ]
    },
    {
        "input": [
            288,
            310,
            -12,
            -131,
            131.54847015454038
        ],
        "output": [
            0,
            0,
            1,
            0
        ]
    },
    {
        "input": [
            320.5,
            120.5,
            220.5,
            -129.5,
            255.71566240650964
        ],
        "output": [
            0,
            0,
            0,
            1
        ]
    },
    {
        "input": [
            353,
            153,
            253,
            -97,
            270.9575612526803
        ],
        "output": [
            0,
            0,
            0,
            1
        ]
    },
    {
        "input": [
            345.5,
            145.5,
            245.5,
            -104.5,
            266.81547931107747
        ],
        "output": [
            0,
            0,
            0,
            1
        ]
    },
    {
        "input": [
            330.5,
            130.5,
            230.5,
            -119.5,
            259.6353211718313
        ],
        "output": [
            0,
            0,
            0,
            1
        ]
    },
    {
        "input": [
            235,
            235,
            -265,
            -15,
            265.42418879973997
        ],
        "output": [
            0,
            1,
            0,
            0
        ]
    },
    {
        "input": [
            262.5,
            262.5,
            -237.5,
            12.5,
            237.8287198805056
        ],
        "output": [
            0,
            1,
            0,
            0
        ]
    },
    {
        "input": [
            365.5,
            165.5,
            265.5,
            -84.5,
            278.62250447514106
        ],
        "output": [
            0,
            0,
            0,
            1
        ]
    },
    {
        "input": [
            255.5,
            342.5,
            -44.5,
            -98.5,
            108.0856142139184
        ],
        "output": [
            0,
            0,
            1,
            0
        ]
    },
    {
        "input": [
            252.5,
            315.5,
            -47.5,
            265.5,
            269.715590947205
        ],
        "output": [
            1,
            0,
            0,
            0
        ]
    },
    {
        "input": [
            237.5,
            237.5,
            -262.5,
            -12.5,
            262.797450520358
        ],
        "output": [
            0,
            1,
            0,
            0
        ]
    },
    {
        "input": [
            318,
            280,
            18,
            -161,
            162.00308639035245
        ],
        "output": [
            0,
            0,
            1,
            0
        ]
    },
    {
        "input": [
            305.5,
            105.5,
            205.5,
            -144.5,
            251.21803279223408
        ],
        "output": [
            0,
            0,
            0,
            1
        ]
    },
    {
        "input": [
            297.5,
            297.5,
            -202.5,
            47.5,
            207.99639419951492
        ],
        "output": [
            0,
            1,
            0,
            0
        ]
    },
    {
        "input": [
            302.5,
            302.5,
            -197.5,
            52.5,
            204.35875317685807
        ],
        "output": [
            0,
            1,
            0,
            0
        ]
    },
    {
        "input": [
            290,
            278,
            -10,
            228,
            228.21919288263203
        ],
        "output": [
            1,
            0,
            0,
            0
        ]
    },
    {
        "input": [
            423,
            223,
            323,
            -27,
            324.1265185078197
        ],
        "output": [
            0,
            0,
            0,
            1
        ]
    },
    {
        "input": [
            210,
            210,
            -290,
            -40,
            292.7456233660889
        ],
        "output": [
            0,
            1,
            0,
            0
        ]
    },
    {
        "input": [
            230,
            230,
            -270,
            -20,
            270.7397274136177
        ],
        "output": [
            0,
            1,
            0,
            0
        ]
    },
    {
        "input": [
            330,
            330,
            -170,
            80,
            187.88294228055935
        ],
        "output": [
            0,
            1,
            0,
            0
        ]
    },
    {
        "input": [
            315,
            253,
            15,
            203,
            203.55343278854326
        ],
        "output": [
            1,
            0,
            0,
            0
        ]
    },
    {
        "input": [
            327.5,
            327.5,
            -172.5,
            77.5,
            189.10975649077443
        ],
        "output": [
            0,
            1,
            0,
            0
        ]
    },
    {
        "input": [
            322.5,
            245.5,
            22.5,
            195.5,
            196.79049773807677
        ],
        "output": [
            1,
            0,
            0,
            0
        ]
    },
    {
        "input": [
            263,
            335,
            -37,
            -106,
            112.27199116431488
        ],
        "output": [
            0,
            0,
            1,
            0
        ]
    },
    {
        "input": [
            310.5,
            110.5,
            210.5,
            -139.5,
            252.52821624523466
        ],
        "output": [
            0,
            0,
            0,
            1
        ]
    },
    {
        "input": [
            370.5,
            227.5,
            70.5,
            -213.5,
            224.83883116579307
        ],
        "output": [
            0,
            0,
            1,
            0
        ]
    },
    {
        "input": [
            378,
            178,
            278,
            -72,
            287.17242207426534
        ],
        "output": [
            0,
            0,
            0,
            1
        ]
    },
    {
        "input": [
            293,
            93,
            193,
            -157,
            248.79308672067236
        ],
        "output": [
            0,
            0,
            0,
            1
        ]
    },
    {
        "input": [
            343,
            143,
            243,
            -107,
            265.51459470243816
        ],
        "output": [
            0,
            0,
            0,
            1
        ]
    },
    {
        "input": [
            298,
            300,
            -2,
            -141,
            141.01418368376991
        ],
        "output": [
            0,
            0,
            1,
            0
        ]
    },
    {
        "input": [
            320,
            248,
            20,
            198,
            199.00753754569197
        ],
        "output": [
            1,
            0,
            0,
            0
        ]
    },
    {
        "input": [
            297.5,
            270.5,
            -2.5,
            220.5,
            220.51417188017643
        ],
        "output": [
            1,
            0,
            0,
            0
        ]
    },
    {
        "input": [
            380.5,
            180.5,
            280.5,
            -69.5,
            288.9818333390526
        ],
        "output": [
            0,
            0,
            0,
            1
        ]
    },
    {
        "input": [
            310,
            258,
            10,
            208,
            208.24024587000469
        ],
        "output": [
            1,
            0,
            0,
            0
        ]
    },
    {
        "input": [
            317.5,
            317.5,
            -182.5,
            67.5,
            194.58288722290047
        ],
        "output": [
            0,
            1,
            0,
            0
        ]
    },
    {
        "input": [
            355,
            213,
            55,
            163,
            172.02906731131225
        ],
        "output": [
            1,
            0,
            0,
            0
        ]
    },
    {
        "input": [
            282.5,
            285.5,
            -17.5,
            235.5,
            236.14931717030223
        ],
        "output": [
            1,
            0,
            0,
            0
        ]
    },
    {
        "input": [
            325,
            325,
            -175,
            75,
            190.3943276465977
        ],
        "output": [
            0,
            1,
            0,
            0
        ]
    },
    {
        "input": [
            325,
            243,
            25,
            193,
            194.61243536834948
        ],
        "output": [
            1,
            0,
            0,
            0
        ]
    },
    {
        "input": [
            330,
            238,
            30,
            188,
            190.3785702225962
        ],
        "output": [
            1,
            0,
            0,
            0
        ]
    },
    {
        "input": [
            385.5,
            185.5,
            285.5,
            -64.5,
            292.69523398921274
        ],
        "output": [
            0,
            0,
            0,
            1
        ]
    },
    {
        "input": [
            365,
            203,
            65,
            153,
            166.23477373883
        ],
        "output": [
            1,
            0,
            0,
            0
        ]
    },
    {
        "input": [
            302.5,
            265.5,
            2.5,
            215.5,
            215.51450067222854
        ],
        "output": [
            1,
            0,
            0,
            0
        ]
    },
    {
        "input": [
            398,
            198,
            298,
            -52,
            302.50289254815397
        ],
        "output": [
            0,
            0,
            0,
            1
        ]
    },
    {
        "input": [
            365.5,
            232.5,
            65.5,
            -208.5,
            218.5463337601434
        ],
        "output": [
            0,
            0,
            1,
            0
        ]
    },
    {
        "input": [
            335,
            335,
            -165,
            85,
            185.60711193270586
        ],
        "output": [
            0,
            1,
            0,
            0
        ]
    },
    {
        "input": [
            393,
            193,
            293,
            -57,
            298.4928809871351
        ],
        "output": [
            0,
            0,
            0,
            1
        ]
    },
    {
        "input": [
            257.5,
            310.5,
            -42.5,
            260.5,
            263.94412287452053
        ],
        "output": [
            1,
            0,
            0,
            0
        ]
    },
    {
        "input": [
            250,
            318,
            -50,
            268,
            272.6242835845699
        ],
        "output": [
            1,
            0,
            0,
            0
        ]
    },
    {
        "input": [
            345,
            345,
            -155,
            95,
            181.79658962697843
        ],
        "output": [
            0,
            1,
            0,
            0
        ]
    },
    {
        "input": [
            380.5,
            217.5,
            80.5,
            -223.5,
            237.55525672988168
        ],
        "output": [
            0,
            0,
            1,
            0
        ]
    },
    {
        "input": [
            243,
            355,
            -57,
            -86,
            103.1746092796091
        ],
        "output": [
            0,
            0,
            1,
            0
        ]
    },
    {
        "input": [
            433,
            233,
            333,
            -17,
            333.4336515710434
        ],
        "output": [
            0,
            0,
            0,
            1
        ]
    },
    {
        "input": [
            240,
            240,
            -260,
            -10,
            260.1922366251537
        ],
        "output": [
            0,
            1,
            0,
            0
        ]
    },
    {
        "input": [
            295,
            273,
            -5,
            223,
            223.0560467685196
        ],
        "output": [
            1,
            0,
            0,
            0
        ]
    },
    {
        "input": [
            337.5,
            337.5,
            -162.5,
            87.5,
            184.5602882529175
        ],
        "output": [
            0,
            1,
            0,
            0
        ]
    },
    {
        "input": [
            395.5,
            195.5,
            295.5,
            -54.5,
            300.4837766003349
        ],
        "output": [
            0,
            0,
            0,
            1
        ]
    },
    {
        "input": [
            333,
            265,
            33,
            -176,
            179.06702655709677
        ],
        "output": [
            0,
            0,
            1,
            0
        ]
    },
    {
        "input": [
            290.5,
            90.5,
            190.5,
            -159.5,
            248.4562335704218
        ],
        "output": [
            0,
            0,
            0,
            1
        ]
    },
    {
        "input": [
            312.5,
            255.5,
            12.5,
            205.5,
            205.87981931214142
        ],
        "output": [
            1,
            0,
            0,
            0
        ]
    },
    {
        "input": [
            360.5,
            237.5,
            60.5,
            -203.5,
            212.3028497218066
        ],
        "output": [
            0,
            0,
            1,
            0
        ]
    },
    {
        "input": [
            383,
            215,
            83,
            -226,
            240.75921581530375
        ],
        "output": [
            0,
            0,
            1,
            0
        ]
    },
    {
        "input": [
            335.5,
            262.5,
            35.5,
            -178.5,
            181.9958790742252
        ],
        "output": [
            0,
            0,
            1,
            0
        ]
    },
    {
        "input": [
            232.5,
            232.5,
            -267.5,
            -17.5,
            268.07181873520386
        ],
        "output": [
            0,
            1,
            0,
            0
        ]
    },
    {
        "input": [
            338,
            260,
            38,
            -181,
            184.94593804677083
        ],
        "output": [
            0,
            0,
            1,
            0
        ]
    },
    {
        "input": [
            268,
            330,
            -32,
            -111,
            115.52056094046635
        ],
        "output": [
            0,
            0,
            1,
            0
        ]
    },
    {
        "input": [
            370,
            198,
            70,
            148,
            163.7192719260625
        ],
        "output": [
            1,
            0,
            0,
            0
        ]
    },
    {
        "input": [
            400.5,
            200.5,
            300.5,
            -49.5,
            304.549667542094
        ],
        "output": [
            0,
            0,
            0,
            1
        ]
    },
    {
        "input": [
            260.5,
            337.5,
            -39.5,
            -103.5,
            110.78131611422569
        ],
        "output": [
            0,
            0,
            1,
            0
        ]
    },
    {
        "input": [
            430.5,
            230.5,
            330.5,
            -19.5,
            331.0747649700895
        ],
        "output": [
            0,
            0,
            0,
            1
        ]
    },
    {
        "input": [
            290.5,
            307.5,
            -9.5,
            -133.5,
            133.83758814324173
        ],
        "output": [
            0,
            0,
            1,
            0
        ]
    },
    {
        "input": [
            367.5,
            200.5,
            67.5,
            150.5,
            164.9439298670915
        ],
        "output": [
            1,
            0,
            0,
            0
        ]
    },
    {
        "input": [
            285,
            283,
            -15,
            233,
            233.4823333787805
        ],
        "output": [
            1,
            0,
            0,
            0
        ]
    },
    {
        "input": [
            265,
            303,
            -35,
            253,
            255.4094751570505
        ],
        "output": [
            1,
            0,
            0,
            0
        ]
    },
    {
        "input": [
            340.5,
            257.5,
            40.5,
            -183.5,
            187.91620472966136
        ],
        "output": [
            0,
            0,
            1,
            0
        ]
    },
    {
        "input": [
            287.5,
            280.5,
            -12.5,
            230.5,
            230.83868826520393
        ],
        "output": [
            1,
            0,
            0,
            0
        ]
    },
    {
        "input": [
            282.5,
            282.5,
            -217.5,
            32.5,
            219.91475621249248
        ],
        "output": [
            0,
            1,
            0,
            0
        ]
    },
    {
        "input": [
            250.5,
            347.5,
            -49.5,
            -93.5,
            105.7946123391924
        ],
        "output": [
            0,
            0,
            1,
            0
        ]
    },
    {
        "input": [
            428,
            228,
            328,
            -22,
            328.7369769283644
        ],
        "output": [
            0,
            0,
            0,
            1
        ]
    },
    {
        "input": [
            415.5,
            215.5,
            315.5,
            -34.5,
            317.38068624287774
        ],
        "output": [
            0,
            0,
            0,
            1
        ]
    },
    {
        "input": [
            328,
            128,
            228,
            -122,
            258.58847615468096
        ],
        "output": [
            0,
            0,
            0,
            1
        ]
    },
    {
        "input": [
            310.5,
            287.5,
            10.5,
            -153.5,
            153.8587014113924
        ],
        "output": [
            0,
            0,
            1,
            0
        ]
    },
    {
        "input": [
            385.5,
            212.5,
            85.5,
            -228.5,
            243.97233449717203
        ],
        "output": [
            0,
            0,
            1,
            0
        ]
    },
    {
        "input": [
            303,
            103,
            203,
            -147,
            250.63519305955418
        ],
        "output": [
            0,
            0,
            0,
            1
        ]
    },
    {
        "input": [
            292.5,
            275.5,
            -7.5,
            225.5,
            225.62468836543576
        ],
        "output": [
            1,
            0,
            0,
            0
        ]
    },
    {
        "input": [
            320.5,
            277.5,
            20.5,
            -163.5,
            164.78015657232518
        ],
        "output": [
            0,
            0,
            1,
            0
        ]
    },
    {
        "input": [
            343,
            255,
            43,
            -186,
            190.90573590125572
        ],
        "output": [
            0,
            0,
            1,
            0
        ]
    },
    {
        "input": [
            245.5,
            352.5,
            -54.5,
            -88.5,
            103.93507588874894
        ],
        "output": [
            0,
            0,
            1,
            0
        ]
    },
    {
        "input": [
            212.5,
            212.5,
            -287.5,
            -37.5,
            289.93533761858004
        ],
        "output": [
            0,
            1,
            0,
            0
        ]
    },
    {
        "input": [
            277.5,
            290.5,
            -22.5,
            240.5,
            241.5502018214847
        ],
        "output": [
            1,
            0,
            0,
            0
        ]
    },
    {
        "input": [
            248,
            350,
            -52,
            -91,
            104.80935072788114
        ],
        "output": [
            0,
            0,
            1,
            0
        ]
    },
    {
        "input": [
            333,
            133,
            233,
            -117,
            260.725909721301
        ],
        "output": [
            0,
            0,
            0,
            1
        ]
    },
    {
        "input": [
            390.5,
            190.5,
            290.5,
            -59.5,
            296.5307741196519
        ],
        "output": [
            0,
            0,
            0,
            1
        ]
    },
    {
        "input": [
            350,
            350,
            -150,
            100,
            180.27756377319946
        ],
        "output": [
            0,
            1,
            0,
            0
        ]
    },
    {
        "input": [
            250,
            250,
            -250,
            0,
            250
        ],
        "output": [
            0,
            1,
            0,
            0
        ]
    },
    {
        "input": [
            340.5,
            140.5,
            240.5,
            -109.5,
            264.2546120694963
        ],
        "output": [
            0,
            0,
            0,
            1
        ]
    },
    {
        "input": [
            260,
            308,
            -40,
            258,
            261.0823624835657
        ],
        "output": [
            1,
            0,
            0,
            0
        ]
    },
    {
        "input": [
            262.5,
            305.5,
            -37.5,
            255.5,
            258.2372939759089
        ],
        "output": [
            1,
            0,
            0,
            0
        ]
    },
    {
        "input": [
            318,
            118,
            218,
            -132,
            254.8489748851268
        ],
        "output": [
            0,
            0,
            0,
            1
        ]
    },
    {
        "input": [
            295.5,
            95.5,
            195.5,
            -154.5,
            249.17965406509416
        ],
        "output": [
            0,
            0,
            0,
            1
        ]
    },
    {
        "input": [
            340,
            228,
            40,
            178,
            182.43903091169938
        ],
        "output": [
            1,
            0,
            0,
            0
        ]
    },
    {
        "input": [
            300,
            300,
            -200,
            50,
            206.15528128088303
        ],
        "output": [
            0,
            1,
            0,
            0
        ]
    },
    {
        "input": [
            332.5,
            332.5,
            -167.5,
            82.5,
            186.7150234983784
        ],
        "output": [
            0,
            1,
            0,
            0
        ]
    },
    {
        "input": [
            280.5,
            317.5,
            -19.5,
            -123.5,
            125.02999640086374
        ],
        "output": [
            0,
            0,
            1,
            0
        ]
    },
    {
        "input": [
            373,
            225,
            73,
            -216,
            228.0021929719098
        ],
        "output": [
            0,
            0,
            1,
            0
        ]
    },
    {
        "input": [
            363,
            235,
            63,
            -206,
            215.41819793137256
        ],
        "output": [
            0,
            0,
            1,
            0
        ]
    },
    {
        "input": [
            215,
            215,
            -285,
            -35,
            287.14108030722457
        ],
        "output": [
            0,
            1,
            0,
            0
        ]
    },
    {
        "input": [
            315.5,
            282.5,
            15.5,
            -158.5,
            159.25608308632985
        ],
        "output": [
            0,
            0,
            1,
            0
        ]
    },
    {
        "input": [
            388,
            188,
            288,
            -62,
            294.59803122220626
        ],
        "output": [
            0,
            0,
            0,
            1
        ]
    },
    {
        "input": [
            425.5,
            225.5,
            325.5,
            -24.5,
            326.4207407625931
        ],
        "output": [
            0,
            0,
            0,
            1
        ]
    },
    {
        "input": [
            330.5,
            267.5,
            30.5,
            -173.5,
            176.16043823742038
        ],
        "output": [
            0,
            0,
            1,
            0
        ]
    },
    {
        "input": [
            255,
            255,
            -245,
            5,
            245.05101509685693
        ],
        "output": [
            0,
            1,
            0,
            0
        ]
    },
    {
        "input": [
            300,
            268,
            0,
            218,
            218
        ],
        "output": [
            1,
            0,
            0,
            0
        ]
    },
    {
        "input": [
            383,
            183,
            283,
            -67,
            290.82297020696285
        ],
        "output": [
            0,
            0,
            0,
            1
        ]
    },
    {
        "input": [
            362.5,
            205.5,
            62.5,
            155.5,
            167.59027418081277
        ],
        "output": [
            1,
            0,
            0,
            0
        ]
    },
    {
        "input": [
            317.5,
            250.5,
            17.5,
            200.5,
            201.2622667069016
        ],
        "output": [
            1,
            0,
            0,
            0
        ]
    },
    {
        "input": [
            295.5,
            302.5,
            -4.5,
            -138.5,
            138.57308540982984
        ],
        "output": [
            0,
            0,
            1,
            0
        ]
    },
    {
        "input": [
            275,
            275,
            -225,
            25,
            226.38462845343543
        ],
        "output": [
            0,
            1,
            0,
            0
        ]
    },
    {
        "input": [
            313,
            285,
            13,
            -156,
            156.54072952429985
        ],
        "output": [
            0,
            0,
            1,
            0
        ]
    },
    {
        "input": [
            368,
            168,
            268,
            -82,
            280.26416110519733
        ],
        "output": [
            0,
            0,
            0,
            1
        ]
    },
    {
        "input": [
            272.5,
            295.5,
            -27.5,
            245.5,
            247.03542256121895
        ],
        "output": [
            1,
            0,
            0,
            0
        ]
    },
    {
        "input": [
            340,
            340,
            -160,
            90,
            183.5755975068582
        ],
        "output": [
            0,
            1,
            0,
            0
        ]
    },
    {
        "input": [
            240.5,
            357.5,
            -59.5,
            -83.5,
            102.5304832720494
        ],
        "output": [
            0,
            0,
            1,
            0
        ]
    },
    {
        "input": [
            252.5,
            252.5,
            -247.5,
            2.5,
            247.512625940577
        ],
        "output": [
            0,
            1,
            0,
            0
        ]
    },
    {
        "input": [
            283,
            315,
            -17,
            -126,
            127.1416532848303
        ],
        "output": [
            0,
            0,
            1,
            0
        ]
    },
    {
        "input": [
            360.5,
            160.5,
            260.5,
            -89.5,
            275.4460019677178
        ],
        "output": [
            0,
            0,
            0,
            1
        ]
    },
    {
        "input": [
            360,
            208,
            60,
            158,
            169.00887550658396
        ],
        "output": [
            1,
            0,
            0,
            0
        ]
    },
    {
        "input": [
            257.5,
            257.5,
            -242.5,
            7.5,
            242.61595166023193
        ],
        "output": [
            0,
            1,
            0,
            0
        ]
    },
    {
        "input": [
            308,
            108,
            208,
            -142,
            251.8491612056709
        ],
        "output": [
            0,
            0,
            0,
            1
        ]
    },
    {
        "input": [
            347.5,
            220.5,
            47.5,
            170.5,
            176.99293771221494
        ],
        "output": [
            1,
            0,
            0,
            0
        ]
    },
    {
        "input": [
            227.5,
            227.5,
            -272.5,
            -22.5,
            273.4273212391183
        ],
        "output": [
            0,
            1,
            0,
            0
        ]
    },
    {
        "input": [
            267.5,
            267.5,
            -232.5,
            17.5,
            233.15767197328077
        ],
        "output": [
            0,
            1,
            0,
            0
        ]
    },
    {
        "input": [
            307.5,
            307.5,
            -192.5,
            57.5,
            200.9042060286444
        ],
        "output": [
            0,
            1,
            0,
            0
        ]
    },
    {
        "input": [
            267.5,
            300.5,
            -32.5,
            250.5,
            252.59948535181144
        ],
        "output": [
            1,
            0,
            0,
            0
        ]
    },
    {
        "input": [
            373,
            173,
            273,
            -77,
            283.6511942509673
        ],
        "output": [
            0,
            0,
            0,
            1
        ]
    },
    {
        "input": [
            270.5,
            327.5,
            -29.5,
            -113.5,
            117.27105354690048
        ],
        "output": [
            0,
            0,
            1,
            0
        ]
    },
    {
        "input": [
            260,
            260,
            -240,
            10,
            240.20824298928628
        ],
        "output": [
            0,
            1,
            0,
            0
        ]
    },
    {
        "input": [
            403,
            203,
            303,
            -47,
            306.62354769325856
        ],
        "output": [
            0,
            0,
            0,
            1
        ]
    },
    {
        "input": [
            217.5,
            217.5,
            -282.5,
            -32.5,
            284.36332393612224
        ],
        "output": [
            0,
            1,
            0,
            0
        ]
    },
    {
        "input": [
            287.5,
            287.5,
            -212.5,
            37.5,
            215.78345627040085
        ],
        "output": [
            0,
            1,
            0,
            0
        ]
    },
    {
        "input": [
            242.5,
            242.5,
            -257.5,
            -7.5,
            257.60920014626805
        ],
        "output": [
            0,
            1,
            0,
            0
        ]
    },
    {
        "input": [
            225,
            225,
            -275,
            -25,
            276.1340254296815
        ],
        "output": [
            0,
            1,
            0,
            0
        ]
    },
    {
        "input": [
            293,
            305,
            -7,
            -136,
            136.1800279042415
        ],
        "output": [
            0,
            0,
            1,
            0
        ]
    },
    {
        "input": [
            332.5,
            235.5,
            32.5,
            185.5,
            188.32551606195057
        ],
        "output": [
            1,
            0,
            0,
            0
        ]
    },
    {
        "input": [
            375.5,
            222.5,
            75.5,
            -218.5,
            231.1763396197803
        ],
        "output": [
            0,
            0,
            1,
            0
        ]
    },
    {
        "input": [
            292.5,
            292.5,
            -207.5,
            42.5,
            211.80769579975134
        ],
        "output": [
            0,
            1,
            0,
            0
        ]
    },
    {
        "input": [
            350.5,
            247.5,
            50.5,
            -193.5,
            199.98124912101133
        ],
        "output": [
            0,
            0,
            1,
            0
        ]
    },
    {
        "input": [
            357.5,
            210.5,
            57.5,
            160.5,
            170.4890025778789
        ],
        "output": [
            1,
            0,
            0,
            0
        ]
    },
    {
        "input": [
            313,
            113,
            213,
            -137,
            253.25481239257823
        ],
        "output": [
            0,
            0,
            0,
            1
        ]
    },
    {
        "input": [
            413,
            213,
            313,
            -37,
            315.1793140420227
        ],
        "output": [
            0,
            0,
            0,
            1
        ]
    },
    {
        "input": [
            372.5,
            195.5,
            72.5,
            145.5,
            162.56229575150567
        ],
        "output": [
            1,
            0,
            0,
            0
        ]
    },
    {
        "input": [
            335,
            233,
            35,
            183,
            186.31693428134759
        ],
        "output": [
            1,
            0,
            0,
            0
        ]
    },
    {
        "input": [
            335.5,
            135.5,
            235.5,
            -114.5,
            261.85969525683026
        ],
        "output": [
            0,
            0,
            0,
            1
        ]
    },
    {
        "input": [
            315,
            315,
            -185,
            65,
            196.08671551127577
        ],
        "output": [
            0,
            1,
            0,
            0
        ]
    },
    {
        "input": [
            323,
            275,
            23,
            -166,
            167.5857989210303
        ],
        "output": [
            0,
            0,
            1,
            0
        ]
    },
    {
        "input": [
            320,
            320,
            -180,
            70,
            193.13207915827965
        ],
        "output": [
            0,
            1,
            0,
            0
        ]
    },
    {
        "input": [
            342.5,
            342.5,
            -157.5,
            92.5,
            182.6540445760783
        ],
        "output": [
            0,
            1,
            0,
            0
        ]
    },
    {
        "input": [
            258,
            340,
            -42,
            -101,
            109.38464243210744
        ],
        "output": [
            0,
            0,
            1,
            0
        ]
    },
    {
        "input": [
            272.5,
            272.5,
            -227.5,
            22.5,
            228.60992979308662
        ],
        "output": [
            0,
            1,
            0,
            0
        ]
    },
    {
        "input": [
            280,
            288,
            -20,
            238,
            238.83885781003056
        ],
        "output": [
            1,
            0,
            0,
            0
        ]
    },
    {
        "input": [
            363,
            163,
            263,
            -87,
            277.01624501101014
        ],
        "output": [
            0,
            0,
            0,
            1
        ]
    },
    {
        "input": [
            338,
            138,
            238,
            -112,
            263.0361191927831
        ],
        "output": [
            0,
            0,
            0,
            1
        ]
    },
    {
        "input": [
            295,
            295,
            -205,
            45,
            209.88091861815357
        ],
        "output": [
            0,
            1,
            0,
            0
        ]
    },
    {
        "input": [
            353,
            245,
            53,
            -196,
            203.03940504246953
        ],
        "output": [
            0,
            0,
            1,
            0
        ]
    },
    {
        "input": [
            352.5,
            215.5,
            52.5,
            165.5,
            173.62747478437853
        ],
        "output": [
            1,
            0,
            0,
            0
        ]
    },
    {
        "input": [
            308,
            290,
            8,
            -151,
            151.21177202850313
        ],
        "output": [
            0,
            0,
            1,
            0
        ]
    },
    {
        "input": [
            358,
            158,
            258,
            -92,
            273.91239475423527
        ],
        "output": [
            0,
            0,
            0,
            1
        ]
    },
    {
        "input": [
            345,
            223,
            45,
            173,
            178.7568180517879
        ],
        "output": [
            1,
            0,
            0,
            0
        ]
    },
    {
        "input": [
            375.5,
            175.5,
            275.5,
            -74.5,
            285.3953398358144
        ],
        "output": [
            0,
            0,
            0,
            1
        ]
    },
    {
        "input": [
            305,
            305,
            -195,
            55,
            202.6079958935481
        ],
        "output": [
            0,
            1,
            0,
            0
        ]
    },
    {
        "input": [
            345.5,
            252.5,
            45.5,
            -188.5,
            193.91364057229188
        ],
        "output": [
            0,
            0,
            1,
            0
        ]
    },
    {
        "input": [
            377.5,
            190.5,
            77.5,
            140.5,
            160.45715939153354
        ],
        "output": [
            1,
            0,
            0,
            0
        ]
    },
    {
        "input": [
            300.5,
            100.5,
            200.5,
            -149.5,
            250.10097960623824
        ],
        "output": [
            0,
            0,
            0,
            1
        ]
    },
    {
        "input": [
            420.5,
            220.5,
            320.5,
            -29.5,
            321.8547809183514
        ],
        "output": [
            0,
            0,
            0,
            1
        ]
    },
    {
        "input": [
            280,
            280,
            -220,
            30,
            222.03603311174518
        ],
        "output": [
            0,
            1,
            0,
            0
        ]
    },
    {
        "input": [
            270,
            298,
            -30,
            248,
            249.80792621532248
        ],
        "output": [
            1,
            0,
            0,
            0
        ]
    },
    {
        "input": [
            352.5,
            352.5,
            -147.5,
            102.5,
            179.61764946686057
        ],
        "output": [
            0,
            1,
            0,
            0
        ]
    },
    {
        "input": [
            350,
            218,
            50,
            168,
            175.2826289168439
        ],
        "output": [
            1,
            0,
            0,
            0
        ]
    },
    {
        "input": [
            342.5,
            225.5,
            42.5,
            175.5,
            180.57270004073152
        ],
        "output": [
            1,
            0,
            0,
            0
        ]
    },
    {
        "input": [
            275.5,
            322.5,
            -24.5,
            -118.5,
            121.00619818835727
        ],
        "output": [
            0,
            0,
            1,
            0
        ]
    },
    {
        "input": [
            290,
            290,
            -210,
            40,
            213.7755832643195
        ],
        "output": [
            0,
            1,
            0,
            0
        ]
    },
    {
        "input": [
            255,
            313,
            -45,
            263,
            266.8220380703213
        ],
        "output": [
            1,
            0,
            0,
            0
        ]
    },
    {
        "input": [
            277.5,
            277.5,
            -222.5,
            27.5,
            224.1929972144536
        ],
        "output": [
            0,
            1,
            0,
            0
        ]
    },
    {
        "input": [
            325.5,
            125.5,
            225.5,
            -124.5,
            257.58590799964196
        ],
        "output": [
            0,
            0,
            0,
            1
        ]
    },
    {
        "input": [
            350.5,
            150.5,
            250.5,
            -99.5,
            269.5375669549608
        ],
        "output": [
            0,
            0,
            0,
            1
        ]
    },
    {
        "input": [
            347.5,
            347.5,
            -152.5,
            97.5,
            181.0041435989795
        ],
        "output": [
            0,
            1,
            0,
            0
        ]
    },
    {
        "input": [
            305.5,
            292.5,
            5.5,
            -148.5,
            148.60181694716925
        ],
        "output": [
            0,
            0,
            1,
            0
        ]
    },
    {
        "input": [
            368,
            230,
            68,
            -211,
            221.68671588527806
        ],
        "output": [
            0,
            0,
            1,
            0
        ]
    },
    {
        "input": [
            312.5,
            312.5,
            -187.5,
            62.5,
            197.64235376052372
        ],
        "output": [
            0,
            1,
            0,
            0
        ]
    },
    {
        "input": [
            408,
            208,
            308,
            -42,
            310.85044635644323
        ],
        "output": [
            0,
            0,
            0,
            1
        ]
    },
    {
        "input": [
            378,
            220,
            78,
            -221,
            234.3608329051593
        ],
        "output": [
            0,
            0,
            1,
            0
        ]
    },
    {
        "input": [
            253,
            345,
            -47,
            -96,
            106.88779163215975
        ],
        "output": [
            0,
            0,
            1,
            0
        ]
    },
    {
        "input": [
            307.5,
            260.5,
            7.5,
            210.5,
            210.63356807498656
        ],
        "output": [
            1,
            0,
            0,
            0
        ]
    },
    {
        "input": [
            245,
            245,
            -255,
            -5,
            255.04901489713697
        ],
        "output": [
            0,
            1,
            0,
            0
        ]
    },
    {
        "input": [
            323,
            123,
            223,
            -127,
            256.62813563598206
        ],
        "output": [
            0,
            0,
            0,
            1
        ]
    },
    {
        "input": [
            315.5,
            115.5,
            215.5,
            -134.5,
            254.02854170348655
        ],
        "output": [
            0,
            0,
            0,
            1
        ]
    },
    {
        "input": [
            348,
            250,
            48,
            -191,
            196.93907687404246
        ],
        "output": [
            0,
            0,
            1,
            0
        ]
    },
    {
        "input": [
            358,
            240,
            58,
            -201,
            209.2008604188807
        ],
        "output": [
            0,
            0,
            1,
            0
        ]
    },
    {
        "input": [
            270,
            270,
            -230,
            20,
            230.8679276123039
        ],
        "output": [
            0,
            1,
            0,
            0
        ]
    },
    {
        "input": [
            305,
            263,
            5,
            213,
            213.05867736377226
        ],
        "output": [
            1,
            0,
            0,
            0
        ]
    },
    {
        "input": [
            322.5,
            322.5,
            -177.5,
            72.5,
            191.7354948881401
        ],
        "output": [
            0,
            1,
            0,
            0
        ]
    },
    {
        "input": [
            285,
            285,
            -215,
            35,
            217.83020910791964
        ],
        "output": [
            0,
            1,
            0,
            0
        ]
    },
    {
        "input": [
            303,
            295,
            3,
            -146,
            146.03081866510234
        ],
        "output": [
            0,
            0,
            1,
            0
        ]
    },
    {
        "input": [
            278,
            320,
            -22,
            -121,
            122.98373876248843
        ],
        "output": [
            0,
            0,
            1,
            0
        ]
    },
    {
        "input": [
            247.5,
            247.5,
            -252.5,
            -2.5,
            252.5123759343292
        ],
        "output": [
            0,
            1,
            0,
            0
        ]
    },
    {
        "input": [
            327.5,
            240.5,
            27.5,
            190.5,
            192.47467365864009
        ],
        "output": [
            1,
            0,
            0,
            0
        ]
    },
    {
        "input": [
            310,
            310,
            -190,
            60,
            199.24858845171275
        ],
        "output": [
            0,
            1,
            0,
            0
        ]
    }
]